dasheng/__init__.py
dasheng/prepare/wavlist_to_tar.py
dasheng/pretrained/pretrained.py
dasheng/train/audiowebdataset.py
dasheng/train/models.py
dasheng/train/train.py
dasheng/train/utils.py
dasheng-0.0.9.dist-info/licenses/LICENSE
dasheng-0.0.9.dist-info/METADATA
dasheng-0.0.9.dist-info/WHEEL
dasheng-0.0.9.dist-info/entry_points.txt
dasheng-0.0.9.dist-info/top_level.txt
dasheng-0.0.9.dist-info/RECORD
