Metadata-Version: 2.4
Name: dasheng
Version: 0.0.9
Author-email: Heinrich Dinkel <dinkelheinrich@xiaomi.com>, Junbo Zhang <zhangjunbo1@xiaomi.com>
Maintainer-email: Heinrich Dinkel <dinkelheinrich@xiaomi.com>, Junbo Zhang <zhangjunbo1@xiaomi.com>
License:                                  Apache License
Project-URL: Homepage, https://github.com/Richermans/dasheng
Project-URL: Documentation, https://github.com/Richermans/dasheng
Project-URL: Repository, https://github.com/Richermans/dasheng
Project-URL: Issues, https://github.com/Richermans/dasheng/issues
Classifier: Development Status :: 3 - Alpha
Classifier: Intended Audience :: Developers
Classifier: Topic :: Software Development :: Build Tools
Classifier: License :: OSI Approved :: MIT License
Classifier: Programming Language :: Python :: 3
Classifier: Programming Language :: Python :: 3.8
Classifier: Programming Language :: Python :: 3.9
Classifier: Programming Language :: Python :: 3.10
Classifier: Programming Language :: Python :: 3.11
Classifier: Environment :: GPU :: NVIDIA CUDA :: 11.4
Classifier: Environment :: GPU :: NVIDIA CUDA :: 12
Classifier: Topic :: Multimedia :: Sound/Audio :: Speech
License-File: LICENSE
Requires-Dist: einops
Requires-Dist: numpy
Requires-Dist: pytorch_ignite
Requires-Dist: torch
Requires-Dist: torchaudio
Provides-Extra: train
Requires-Dist: accelerate>=0.28.0; extra == "train"
Requires-Dist: bitsandbytes>=0.35.4; extra == "train"
Requires-Dist: webdataset>=0.2.86; extra == "train"
Requires-Dist: braceexpand>=0.1.7; extra == "train"
Requires-Dist: fire>=0.5.0; extra == "train"
Requires-Dist: loguru>=0.7.2; extra == "train"
Requires-Dist: numpy>=1.24.1; extra == "train"
Requires-Dist: pytorch_ignite>=0.4.13; extra == "train"
Requires-Dist: PyYAML>=6.0.1; extra == "train"
Requires-Dist: torch>=2.1.1; extra == "train"
Requires-Dist: torchaudio>=2.1.1; extra == "train"
Requires-Dist: tqdm>=4.66.1; extra == "train"
Requires-Dist: pandas>=2.0; extra == "train"
Provides-Extra: all
Requires-Dist: dasheng[train]; extra == "all"
Dynamic: license-file
